LICENSE
MANIFEST.in
README.md
setup.cfg
setup.py
bin/correct_gaussian_orientation.py
bin/lsmtool
lsmtool/__init__.py
lsmtool/_logging.py
lsmtool/_version.py
lsmtool/operations_lib.py
lsmtool/skymodel.py
lsmtool/tableio.py
lsmtool.egg-info/PKG-INFO
lsmtool.egg-info/SOURCES.txt
lsmtool.egg-info/dependency_links.txt
lsmtool.egg-info/requires.txt
lsmtool.egg-info/top_level.txt
lsmtool/operations/__init__.py
lsmtool/operations/_cluster.py
lsmtool/operations/_filter.py
lsmtool/operations/_kdtree.py
lsmtool/operations/_meanshift.py
lsmtool/operations/_meanshiftc.py
lsmtool/operations/_tessellate.py
lsmtool/operations/_threshold.py
lsmtool/operations/add.py
lsmtool/operations/compare.py
lsmtool/operations/concatenate.py
lsmtool/operations/group.py
lsmtool/operations/merge.py
lsmtool/operations/move.py
lsmtool/operations/plot.py
lsmtool/operations/remove.py
lsmtool/operations/select.py
lsmtool/operations/setpatchpositions.py
lsmtool/operations/transfer.py
lsmtool/operations/ungroup.py
tests/apparent.sky
tests/concat.sky
tests/no_patches.sky
tests/patches.sky
tests/single_spectralindx.sky
tests/test_lsmtool.py
tests/validation.py