Metadata-Version: 2.1
Name: lsmtool
Version: 1.5.1
Summary: The LOFAR Local Sky Model Tool
Home-page: https://git.astron.nl/RD/LSMTool
Author: David Rafferty
Author-email: drafferty@hs.uni-hamburg.de
License: GPL
Project-URL: Documentation, https://lsmtool.readthedocs.io/en/latest/
Project-URL: Source, https://git.astron.nl/RD/LSMTool
Platform: any
Classifier: Development Status :: 5 - Production/Stable
Classifier: Programming Language :: Python
Classifier: Natural Language :: English
Classifier: Intended Audience :: Science/Research
Classifier: Topic :: Scientific/Engineering :: Astronomy
Classifier: Topic :: Software Development :: Libraries :: Python Modules
Requires-Python: >=3.7
License-File: LICENSE
Requires-Dist: numpy
Requires-Dist: astropy>=3.2
Requires-Dist: matplotlib>=0.99
Requires-Dist: scipy>=0.11
Requires-Dist: everybeam
